xj_equipment/__init__.py
xj_equipment/admin.py
xj_equipment/apps.py
xj_equipment/config.py
xj_equipment/customValidator.py
xj_equipment/models.py
xj_equipment/urls.py
xj_equipment/apis/__init__.py
xj_equipment/apis/equipment.py
xj_equipment/apis/equipment_configure.py
xj_equipment/apis/equipment_types.py
xj_equipment/apis/equipment_use_map.py
xj_equipment/apis/equipment_warning.py
xj_equipment/apis/equopment_record.py
xj_equipment/apis/equopment_statistic.py
xj_equipment/command/__init__.py
xj_equipment/command/report.py
xj_equipment/services/__init__.py
xj_equipment/services/equipment_record_service.py
xj_equipment/services/equipment_service.py
xj_equipment/services/equipment_statistic_service.py
xj_equipment/services/equipment_warning_service.py
xj_equipment/services/service.py
xj_equipment/utils/__init__.py
xj_equipment/utils/custom_authentication_wrapper.py
xj_equipment/utils/custom_authorization.py
xj_equipment/utils/custom_exception.py
xj_equipment/utils/custom_pagination.py
xj_equipment/utils/custom_response.py
xj_equipment/utils/model_handle.py
xj_equipment/utils/util.py
xj_equipment-1.0.19.dist-info/METADATA
xj_equipment-1.0.19.dist-info/WHEEL
xj_equipment-1.0.19.dist-info/top_level.txt
xj_equipment-1.0.19.dist-info/RECORD
