Metadata-Version: 2.1
Name: xj-equipment
Version: 1.0.19
Summary: 设备模块-修复设备列表问题
Home-page: UNKNOWN
Author: 赵向明
Author-email: sieyoo@163.com
Maintainer: 孙楷炎
Maintainer-email: sky4834@163.com
License: apache 3.0
Platform: UNKNOWN
